{
  "_class": "bitmap",
  "clippingMask": "{{0, 0}, {1, 1}}",
  "do_objectID": "FD039D0A-3FD1-4096-87CB-37A8092F4021",
  "exportOptions": {
    "_class": "exportOptions",
    "exportFormats": [
    ],
    "includedLayerIds": [
    ],
    "layerOptions": 0,
    "shouldTrim": false
  },
  "fillReplacesImage": false,
  "frame": {
    "_class": "rect",
    "constrainProportions": false,
    "height": 31,
    "width": 75,
    "x": 134,
    "y": 15
  },
  "image": {
    "_class": "MSJSONFileReference",
    "_ref": "images/aba106a0fc31067f33258aced8883dd2291f7a86",
    "_ref_class": "MSImageData"
  },
  "isFlippedHorizontal": false,
  "isFlippedVertical": false,
  "isLocked": false,
  "isVisible": true,
  "layerListExpandedType": 0,
  "name": "Bitmap",
  "nameIsFixed": false,
  "resizingConstraint": 13,
  "resizingType": 0,
  "rotation": 0,
  "shouldBreakMaskChain": false,
  "style": {
    "_class": "style",
    "endDecorationType": 0,
    "miterLimit": 10,
    "startDecorationType": 0
  }
}