{
  "_class": "group",
  "do_objectID": "EA00278D-1810-4E73-B16E-D4ECE9A3022C",
  "exportOptions": {
    "_class": "exportOptions",
    "exportFormats": [
    ],
    "includedLayerIds": [
    ],
    "layerOptions": 0,
    "shouldTrim": false
  },
  "frame": {
    "_class": "rect",
    "constrainProportions": false,
    "height": 205,
    "width": 293,
    "x": 0,
    "y": 0
  },
  "hasClickThrough": false,
  "isFlippedHorizontal": false,
  "isFlippedVertical": false,
  "isLocked": false,
  "isVisible": true,
  "layerListExpandedType": 0,
  "layers": [
    {
      "class": "shapeGroup",
      "id": "0670EF04-8851-415D-9F0A-B2645310DAE2"
    },
    {
      "class": "shapeGroup",
      "id": "B43FDAEC-C544-46A3-B0CB-0A9E5CAACE17"
    },
    {
      "class": "bitmap",
      "id": "E80CAC95-82FB-401B-97BE-3A0B7A38841D"
    }
  ],
  "name": "Group",
  "nameIsFixed": false,
  "resizingConstraint": 63,
  "resizingType": 0,
  "rotation": 0,
  "shouldBreakMaskChain": false,
  "style": {
    "_class": "style",
    "endDecorationType": 0,
    "miterLimit": 10,
    "startDecorationType": 0
  }
}